aiclipal/__init__.py
aiclipal/__main__.py
aiclipal/aiclipal.py
aiclipal-0.0.8.dist-info/LICENSE
aiclipal-0.0.8.dist-info/METADATA
aiclipal-0.0.8.dist-info/WHEEL
aiclipal-0.0.8.dist-info/entry_points.txt
aiclipal-0.0.8.dist-info/top_level.txt
aiclipal-0.0.8.dist-info/RECORD
